dictionary/__init__.py
dictionary/britannica.py
dictionary/tools.py
britannica_dictionary-0.1.0.dist-info/METADATA
britannica_dictionary-0.1.0.dist-info/WHEEL
britannica_dictionary-0.1.0.dist-info/top_level.txt
britannica_dictionary-0.1.0.dist-info/RECORD
