Metadata-Version: 2.1
Name: britannica-dictionary
Version: 0.1.0
Summary: A Python package to crawl Britannica Dictionary for word entries, definitions, and more.
Home-page: https://github.com/Esubaalew/Dictionary
Author: Esualew Chekol
Author-email: esubalewchekol6@gmail.com
Classifier: Programming Language :: Python :: 3
Classifier: License :: OSI Approved :: MIT License
Classifier: Operating System :: OS Independent
Requires-Python: >=3.6
Requires-Dist: beautifulsoup4
Requires-Dist: requests
